[
  {
    "id": 1,
    "text": "📢 เว็บไซต์ของเรากำลังอยู่ในขั้นตอนการอัปเดตหน้าเว็บ เวอร์ชันใหม่จะเปิดให้ชมเร็ว ๆ นี้!",
    "status": "updating",
    "lastUpdated": "2025-10-14T07:47:22+07:00"
  },
  {
    "id": 2,
    "text": "🚀 ระบบหลังบ้านพร้อมใช้งานแล้วกว่า 99% และพร้อมรองรับลูกค้าทุกท่าน",
    "status": "ready",
    "lastUpdated": "2025-10-14T07:47:22+07:00"
  },
  {
    "id": 3,
    "text": "💬 ลูกค้าสามารถติดต่อเพื่อพูดคุย หรือต้องการเริ่มโปรเจกต์ใหม่ได้ทันที",
    "status": "active",
    "lastUpdated": "2025-10-14T07:47:22+07:00"
  },
  {
    "id": 4,
    "text": "📞 ช่องทางติดต่อหลักของเราคือ LINE Official: https://lin.ee/G8s8rKp",
    "status": "active",
    "lastUpdated": "2025-10-14T07:47:22+07:00"
  },
  {
    "id": 5,
    "text": "🙏 ขอบคุณที่ไว้วางใจ JP-VISOUL-DOCE ในการออกแบบและพัฒนาระบบของคุณ",
    "status": "active",
    "lastUpdated": "2025-10-14T07:47:22+07:00"
  }
]
